fhirpower.py
fhirpower-0.1.0.dist-info/METADATA
fhirpower-0.1.0.dist-info/WHEEL
fhirpower-0.1.0.dist-info/top_level.txt
fhirpower-0.1.0.dist-info/RECORD
